soonerdb/__init__.py
soonerdb/cli.py
soonerdb/io.py
soonerdb/memtable.py
soonerdb/merge.py
soonerdb/soonerdb.py
soonerdb/sstable.py
soonerdb/wal.py
soonerdb-0.1.2.dist-info/AUTHORS.rst
soonerdb-0.1.2.dist-info/LICENSE
soonerdb-0.1.2.dist-info/METADATA
soonerdb-0.1.2.dist-info/WHEEL
soonerdb-0.1.2.dist-info/entry_points.txt
soonerdb-0.1.2.dist-info/top_level.txt
soonerdb-0.1.2.dist-info/RECORD
