Metadata-Version: 2.1
Name: soonerdb
Version: 0.1.2
Summary: A LSM-Tree key/value database in Python
Home-page: https://github.com/fgmacedo/soonerdb
Author: Fernando Macedo
Author-email: fgmacedo@gmail.com
License: MIT license
Keywords: soonerdb
Platform: UNKNOWN
Classifier: Development Status :: 2 - Pre-Alpha
Classifier: Intended Audience :: Developers
Classifier: License :: OSI Approved :: MIT License
Classifier: Natural Language :: English
Classifier: Programming Language :: Python :: 3
Classifier: Programming Language :: Python :: 3.6
Classifier: Programming Language :: Python :: 3.7
Classifier: Programming Language :: Python :: 3.8
Classifier: Programming Language :: Python :: 3.9
Requires-Python: >=3.5
Requires-Dist: Click (>=7.0)
Requires-Dist: sortedcontainers (<2.4,>=2.3.0)
